bolt/__init__.py
bolt/bolt_router.py
bolt_sdk-2.1.7.dist-info/LICENSE
bolt_sdk-2.1.7.dist-info/METADATA
bolt_sdk-2.1.7.dist-info/WHEEL
bolt_sdk-2.1.7.dist-info/top_level.txt
bolt_sdk-2.1.7.dist-info/RECORD
