Metadata-Version: 2.1
Name: bolt-sdk
Version: 2.1.7
Summary: Bolt Python SDK
Home-page: https://gitlab.com/projectn-oss/projectn-bolt-python
Author: Project N
License: UNKNOWN
Platform: UNKNOWN
Classifier: Programming Language :: Python :: 3
Classifier: Operating System :: OS Independent
Classifier: License :: OSI Approved :: Apache Software License
Classifier: Topic :: Software Development :: Libraries
Requires-Python: >=2.7
Requires-Dist: boto3
Requires-Dist: botocore
